setup.py
deos/__init__.py
deos.egg-info/PKG-INFO
deos.egg-info/SOURCES.txt
deos.egg-info/dependency_links.txt
deos.egg-info/not-zip-safe
deos.egg-info/top_level.txt