Metadata-Version: 1.0
Name: deos
Version: 0.1
Summary: decentralized operating system
Home-page: https://github.com/desantis/python-deos
Author: Andrew T. DeSantis
Author-email: atd@deos.org
License: MIT
Platform: UNKNOWN
